odoo/addons/product_attribute_auto_add/README.rst
odoo/addons/product_attribute_auto_add/__init__.py
odoo/addons/product_attribute_auto_add/__manifest__.py
odoo/addons/product_attribute_auto_add/i18n/it.po
odoo/addons/product_attribute_auto_add/i18n/product_attribute_auto_add.pot
odoo/addons/product_attribute_auto_add/models/__init__.py
odoo/addons/product_attribute_auto_add/models/product_attribute.py
odoo/addons/product_attribute_auto_add/models/product_attribute_value.py
odoo/addons/product_attribute_auto_add/models/product_template.py
odoo/addons/product_attribute_auto_add/readme/CONFIGURE.md
odoo/addons/product_attribute_auto_add/readme/CONTRIBUTORS.md
odoo/addons/product_attribute_auto_add/readme/DESCRIPTION.md
odoo/addons/product_attribute_auto_add/readme/HISTORY.md
odoo/addons/product_attribute_auto_add/readme/USAGE.md
odoo/addons/product_attribute_auto_add/static/description/icon.png
odoo/addons/product_attribute_auto_add/static/description/index.html
odoo/addons/product_attribute_auto_add/static/img/usage.png
odoo/addons/product_attribute_auto_add/tests/__init__.py
odoo/addons/product_attribute_auto_add/tests/test_product_attribute_value.py
odoo/addons/product_attribute_auto_add/views/product_attribute_views.xml
odoo/addons/product_attribute_auto_add/views/product_template_views.xml
odoo_addon_product_attribute_auto_add-17.0.1.0.0.7.dist-info/METADATA
odoo_addon_product_attribute_auto_add-17.0.1.0.0.7.dist-info/WHEEL
odoo_addon_product_attribute_auto_add-17.0.1.0.0.7.dist-info/top_level.txt
odoo_addon_product_attribute_auto_add-17.0.1.0.0.7.dist-info/RECORD
