Metadata-Version: 2.1
Name: odoo-addon-product_attribute_auto_add
Version: 17.0.1.0.0.7
Requires-Python: >=3.10
Requires-Dist: odoo>=17.0a,<17.1dev
Summary: Add new attribute values to product templates automatically
Home-page: https://github.com/OCA/product-attribute
License: LGPL-3
Author: Cetmix, Odoo Community Association (OCA)
Author-email: support@odoo-community.org
Classifier: Programming Language :: Python
Classifier: Framework :: Odoo
Classifier: Framework :: Odoo :: 17.0
Classifier: License :: OSI Approved :: GNU Lesser General Public License v3 (LGPLv3)
